story_children_video_maker/__init__.py
story_children_video_maker/config/config.json
story_children_video_maker/pipeToMaker.py
story_children_video_maker/utils/__init__.py
story_children_video_maker/utils/setup.py
story_children_video_maker-0.1.2.dist-info/METADATA
story_children_video_maker-0.1.2.dist-info/WHEEL
story_children_video_maker-0.1.2.dist-info/RECORD
