Metadata-Version: 2.3
Name: story-children-video-maker
Version: 0.1.2
Summary: 
Author: William Ferreira
Author-email: 33575357+illiamw@users.noreply.github.com
Requires-Python: >=3.11
Classifier: Programming Language :: Python :: 3
Classifier: Programming Language :: Python :: 3.11
Classifier: Programming Language :: Python :: 3.12
Classifier: Programming Language :: Python :: 3.13
Requires-Dist: moviepy (>=2.1.2,<3.0.0)
